sota/__init__.py
sota-0.1.0.dist-info/DESCRIPTION.rst
sota-0.1.0.dist-info/METADATA
sota-0.1.0.dist-info/RECORD
sota-0.1.0.dist-info/WHEEL
sota-0.1.0.dist-info/metadata.json
sota-0.1.0.dist-info/top_level.txt
sota-0.1.0.dist-info/zip-safe
